pi.py
pi_by_heart-1.0.7.dist-info/licenses/LICENSE
pi_by_heart-1.0.7.dist-info/METADATA
pi_by_heart-1.0.7.dist-info/WHEEL
pi_by_heart-1.0.7.dist-info/entry_points.txt
pi_by_heart-1.0.7.dist-info/top_level.txt
pi_by_heart-1.0.7.dist-info/RECORD
