Metadata-Version: 2.4
Name: pi-by-heart
Version: 1.0.7
Summary: A simple pi memorization game
Author-email: menisadi <menisadi@gmail.com>
License:                     GNU GENERAL PUBLIC LICENSE
Project-URL: Homepage, https://github.com/menisadi/pi-by-heart
Keywords: game,python,pi,mpmath,pyfiglet
Requires-Python: >=3.10
License-File: LICENSE
Requires-Dist: mpmath>=1.0
Requires-Dist: pyfiglet>=1.0
Dynamic: license-file
